README
setup.py
jersey.egg-info/PKG-INFO
jersey.egg-info/SOURCES.txt
jersey.egg-info/dependency_links.txt
jersey.egg-info/requires.txt
jersey.egg-info/top_level.txt
lib/__init__.py
lib/_version.py
lib/cli.py
lib/inet.py
lib/log.py
lib/cases/__init__.py
lib/cases/base.py
lib/cases/test_cli.py
lib/cases/test_inet.py
lib/cases/test_log.py