Metadata-Version: 1.1
Name: jersey
Version: 0.1.5
Summary: Jersey Core Libraries
Home-page: http://jersey.olix0r.net
Author: Oliver Gould
Author-email: jersey@olix0r.net
License: BSD
Platform: UNKNOWN
Classifier: Development Status :: 4 - Beta
Classifier: Environment :: Console
Classifier: Framework :: Twisted
Classifier: Intended Audience :: Developers
Classifier: License :: OSI Approved :: BSD License
Classifier: Programming Language :: Python
Provides: jersey
Provides: jersey.cli
Provides: jersey.inet
Provides: jersey.log
